README.md
setup.py
onebusaway/__init__.py
onebusaway/client.py
onebusaway/client_json.py
onebusaway/exceptions.py
onebusaway/models.py
onebusaway/modelsMTA.py
onebusaway/utils.py
onebusaway_unofficial.egg-info/PKG-INFO
onebusaway_unofficial.egg-info/SOURCES.txt
onebusaway_unofficial.egg-info/dependency_links.txt
onebusaway_unofficial.egg-info/top_level.txt
tests/test_client.py
tests/test_models.py