Metadata-Version: 2.1
Name: onebusaway-unofficial
Version: 1.0.2
Summary: The OneBusAway Python Client (unofficial) is a Python library for interacting with the OneBusAway API. It provides a simple and convenient way to access real-time transit data, schedules, and other information from various transit agencies.
Home-page: https://github.com/CheeksTheGeek/onebusaway-python
Author: Chaitanya Sharma
License: MIT
